{
  "v": "5.1.16",
  "fr": 25,
  "ip": 0,
  "op": 99,
  "w": 1710,
  "h": 1494,
  "nm": "Comp 1",
  "ddd": 0,
  "assets": [
    {
      "id": "image_0",
      "w": 2552,
      "h": 2889,
      "u": "assets/img/",
      "p": "verified_svg.png",
      "e": 0
    }
  ],
  "layers": [
    {
      "ddd": 0,
      "ind": 1,
      "ty": 4,
      "nm": "red-cube Outlines",
      "sr": 1,
      "ks": {
        "o": {
          "a": 0,
          "k": 100,
          "ix": 11
        },
        "r": {
          "a": 0,
          "k": 0,
          "ix": 10
        },
        "p": {
          "a": 1,
          "k": [
            {
              "i": {
                "x": 0.667,
                "y": 1
              },
              "o": {
                "x": 0.167,
                "y": 0.167
              },
              "n": "0p667_1_0p167_0p167",
              "t": 0,
              "s": [
                1471,
                1221,
                0
              ],
              "e": [
                1471,
                979,
                0
              ],
              "to": [
                0,
                -40.3333320617676,
                0
              ],
              "ti": [
                0,
                0,
                0
              ]
            },
            {
              "i": {
                "x": 0.833,
                "y": 0.833
              },
              "o": {
                "x": 0.333,
                "y": 0
              },
              "n": "0p833_0p833_0p333_0",
              "t": 8,
              "s": [
                1471,
                979,
                0
              ],
              "e": [
                1471,
                1221,
                0
              ],
              "to": [
                0,
                0,
                0
              ],
              "ti": [
                0,
                -40.3333320617676,
                0
              ]
            },
            {
              "i": {
                "x": 0.833,
                "y": 0.833
              },
              "o": {
                "x": 0.167,
                "y": 0.167
              },
              "n": "0p833_0p833_0p167_0p167",
              "t": 16,
              "s": [
                1471,
                1221,
                0
              ],
              "e": [
                1471,
                1221,
                0
              ],
              "to": [
                0,
                0,
                0
              ],
              "ti": [
                0,
                0,
                0
              ]
            },
            {
              "i": {
                "x": 0.667,
                "y": 1
              },
              "o": {
                "x": 0.167,
                "y": 0.167
              },
              "n": "0p667_1_0p167_0p167",
              "t": 26,
              "s": [
                1471,
                1221,
                0
              ],
              "e": [
                1471,
                979,
                0
              ],
              "to": [
                0,
                -40.3333358764648,
                0
              ],
              "ti": [
                0,
                0,
                0
              ]
            },
            {
              "i": {
                "x": 0.833,
                "y": 0.833
              },
              "o": {
                "x": 0.167,
                "y": 0
              },
              "n": "0p833_0p833_0p167_0",
              "t": 32,
              "s": [
                1471,
                979,
                0
              ],
              "e": [
                1471,
                1221,
                0
              ],
              "to": [
                0,
                0,
                0
              ],
              "ti": [
                0,
                -40.3333320617676,
                0
              ]
            },
            {
              "i": {
                "x": 0.833,
                "y": 0.833
              },
              "o": {
                "x": 0.167,
                "y": 0.167
              },
              "n": "0p833_0p833_0p167_0p167",
              "t": 40,
              "s": [
                1471,
                1221,
                0
              ],
              "e": [
                1471,
                1221,
                0
              ],
              "to": [
                0,
                2.33333396911621,
                0
              ],
              "ti": [
                0,
                -40.3333320617676,
                0
              ]
            },
            {
              "i": {
                "x": 0.667,
                "y": 1
              },
              "o": {
                "x": 0.167,
                "y": 0.167
              },
              "n": "0p667_1_0p167_0p167",
              "t": 50,
              "s": [
                1471,
                1221,
                0
              ],
              "e": [
                1471,
                979,
                0
              ],
              "to": [
                0,
                2.33333396911621,
                0
              ],
              "ti": [
                0,
                0,
                0
              ]
            },
            {
              "i": {
                "x": 0.833,
                "y": 0.816
              },
              "o": {
                "x": 0.333,
                "y": 0
              },
              "n": "0p833_0p816_0p333_0",
              "t": 56,
              "s": [
                1471,
                979,
                0
              ],
              "e": [
                1471,
                1221,
                0
              ],
              "to": [
                0,
                0,
                0
              ],
              "ti": [
                0,
                -40.3333320617676,
                0
              ]
            },
            {
              "i": {
                "x": 0.833,
                "y": 0.917
              },
              "o": {
                "x": 0.167,
                "y": 0.167
              },
              "n": "0p833_0p917_0p167_0p167",
              "t": 64,
              "s": [
                1471,
                1221,
                0
              ],
              "e": [
                1471,
                1221,
                0
              ],
              "to": [
                0,
                2.33333396911621,
                0
              ],
              "ti": [
                0,
                -40.3333320617676,
                0
              ]
            },
            {
              "i": {
                "x": 0.667,
                "y": 1
              },
              "o": {
                "x": 0.167,
                "y": 0.167
              },
              "n": "0p667_1_0p167_0p167",
              "t": 73,
              "s": [
                1471,
                1221,
                0
              ],
              "e": [
                1471,
                979,
                0
              ],
              "to": [
                0,
                2.33333396911621,
                0
              ],
              "ti": [
                0,
                0,
                0
              ]
            },
            {
              "i": {
                "x": 0.833,
                "y": 0.833
              },
              "o": {
                "x": 0.333,
                "y": 0
              },
              "n": "0p833_0p833_0p333_0",
              "t": 79,
              "s": [
                1471,
                979,
                0
              ],
              "e": [
                1471,
                1221,
                0
              ],
              "to": [
                0,
                0,
                0
              ],
              "ti": [
                0,
                -40.3333320617676,
                0
              ]
            },
            {
              "t": 87
            }
          ],
          "ix": 2
        },
        "a": {
          "a": 0,
          "k": [
            34,
            36,
            0
          ],
          "ix": 1
        },
        "s": {
          "a": 0,
          "k": [
            238,
            238,
            100
          ],
          "ix": 6
        }
      },
      "ao": 0,
      "shapes": [
        {
          "ty": "gr",
          "it": [
            {
              "ind": 0,
              "ty": "sh",
              "ix": 1,
              "ks": {
                "a": 0,
                "k": {
                  "i": [
                    [
                      0,
                      0
                    ],
                    [
                      0,
                      0
                    ],
                    [
                      0,
                      0
                    ],
                    [
                      0,
                      0
                    ]
                  ],
                  "o": [
                    [
                      0,
                      0
                    ],
                    [
                      0,
                      0
                    ],
                    [
                      0,
                      0
                    ],
                    [
                      0,
                      0
                    ]
                  ],
                  "v": [
                    [
                      15.492,
                      -6.433
                    ],
                    [
                      15.409,
                      24.272
                    ],
                    [
                      -15.492,
                      6.433
                    ],
                    [
                      -15.402,
                      -24.272
                    ]
                  ],
                  "c": true
                },
                "ix": 2
              },
              "nm": "Path 1",
              "mn": "ADBE Vector Shape - Group",
              "hd": false
            },
            {
              "ty": "fl",
              "c": {
                "a": 0,
                "k": [
                  0.510000011968,
                  0.136999990426,
                  0.13300000359,
                  1
                ],
                "ix": 4
              },
              "o": {
                "a": 0,
                "k": 100,
                "ix": 5
              },
              "r": 1,
              "nm": "Fill 1",
              "mn": "ADBE Vector Graphic - Fill",
              "hd": false
            },
            {
              "ty": "tr",
              "p": {
                "a": 0,
                "k": [
                  18.243,
                  44.697
                ],
                "ix": 2
              },
              "a": {
                "a": 0,
                "k": [
                  0,
                  0
                ],
                "ix": 1
              },
              "s": {
                "a": 0,
                "k": [
                  100,
                  100
                ],
                "ix": 3
              },
              "r": {
                "a": 0,
                "k": 0,
                "ix": 6
              },
              "o": {
                "a": 0,
                "k": 100,
                "ix": 7
              },
              "sk": {
                "a": 0,
                "k": 0,
                "ix": 4
              },
              "sa": {
                "a": 0,
                "k": 0,
                "ix": 5
              },
              "nm": "Transform"
            }
          ],
          "nm": "Group 1",
          "np": 2,
          "cix": 2,
          "ix": 1,
          "mn": "ADBE Vector Group",
          "hd": false
        },
        {
          "ty": "gr",
          "it": [
            {
              "ind": 0,
              "ty": "sh",
              "ix": 1,
              "ks": {
                "a": 0,
                "k": {
                  "i": [
                    [
                      0,
                      0
                    ],
                    [
                      0,
                      0
                    ],
                    [
                      0,
                      0
                    ],
                    [
                      0,
                      0
                    ]
                  ],
                  "o": [
                    [
                      0,
                      0
                    ],
                    [
                      0,
                      0
                    ],
                    [
                      0,
                      0
                    ],
                    [
                      0,
                      0
                    ]
                  ],
                  "v": [
                    [
                      15.391,
                      -24.272
                    ],
                    [
                      15.308,
                      6.434
                    ],
                    [
                      -15.391,
                      24.272
                    ],
                    [
                      -15.307,
                      -6.433
                    ]
                  ],
                  "c": true
                },
                "ix": 2
              },
              "nm": "Path 1",
              "mn": "ADBE Vector Shape - Group",
              "hd": false
            },
            {
              "ty": "fl",
              "c": {
                "a": 0,
                "k": [
                  0.663000009574,
                  0.204000001795,
                  0.2,
                  1
                ],
                "ix": 4
              },
              "o": {
                "a": 0,
                "k": 100,
                "ix": 5
              },
              "r": 1,
              "nm": "Fill 1",
              "mn": "ADBE Vector Graphic - Fill",
              "hd": false
            },
            {
              "ty": "tr",
              "p": {
                "a": 0,
                "k": [
                  49.042,
                  44.697
                ],
                "ix": 2
              },
              "a": {
                "a": 0,
                "k": [
                  0,
                  0
                ],
                "ix": 1
              },
              "s": {
                "a": 0,
                "k": [
                  100,
                  100
                ],
                "ix": 3
              },
              "r": {
                "a": 0,
                "k": 0,
                "ix": 6
              },
              "o": {
                "a": 0,
                "k": 100,
                "ix": 7
              },
              "sk": {
                "a": 0,
                "k": 0,
                "ix": 4
              },
              "sa": {
                "a": 0,
                "k": 0,
                "ix": 5
              },
              "nm": "Transform"
            }
          ],
          "nm": "Group 2",
          "np": 2,
          "cix": 2,
          "ix": 2,
          "mn": "ADBE Vector Group",
          "hd": false
        },
        {
          "ty": "gr",
          "it": [
            {
              "ind": 0,
              "ty": "sh",
              "ix": 1,
              "ks": {
                "a": 0,
                "k": {
                  "i": [
                    [
                      0,
                      0
                    ],
                    [
                      0,
                      0
                    ],
                    [
                      0,
                      0
                    ],
                    [
                      0,
                      0
                    ]
                  ],
                  "o": [
                    [
                      0,
                      0
                    ],
                    [
                      0,
                      0
                    ],
                    [
                      0,
                      0
                    ],
                    [
                      0,
                      0
                    ]
                  ],
                  "v": [
                    [
                      30.796,
                      -0.001
                    ],
                    [
                      0.098,
                      17.839
                    ],
                    [
                      -30.796,
                      -0.001
                    ],
                    [
                      -0.098,
                      -17.839
                    ]
                  ],
                  "c": true
                },
                "ix": 2
              },
              "nm": "Path 1",
              "mn": "ADBE Vector Shape - Group",
              "hd": false
            },
            {
              "ty": "fl",
              "c": {
                "a": 0,
                "k": [
                  0.722000002394,
                  0.224000010771,
                  0.224000010771,
                  1
                ],
                "ix": 4
              },
              "o": {
                "a": 0,
                "k": 100,
                "ix": 5
              },
              "r": 1,
              "nm": "Fill 1",
              "mn": "ADBE Vector Graphic - Fill",
              "hd": false
            },
            {
              "ty": "tr",
              "p": {
                "a": 0,
                "k": [
                  33.637,
                  20.425
                ],
                "ix": 2
              },
              "a": {
                "a": 0,
                "k": [
                  0,
                  0
                ],
                "ix": 1
              },
              "s": {
                "a": 0,
                "k": [
                  100,
                  100
                ],
                "ix": 3
              },
              "r": {
                "a": 0,
                "k": 0,
                "ix": 6
              },
              "o": {
                "a": 0,
                "k": 100,
                "ix": 7
              },
              "sk": {
                "a": 0,
                "k": 0,
                "ix": 4
              },
              "sa": {
                "a": 0,
                "k": 0,
                "ix": 5
              },
              "nm": "Transform"
            }
          ],
          "nm": "Group 3",
          "np": 2,
          "cix": 2,
          "ix": 3,
          "mn": "ADBE Vector Group",
          "hd": false
        }
      ],
      "ip": 0,
      "op": 99,
      "st": 0,
      "bm": 0
    },
    {
      "ddd": 0,
      "ind": 2,
      "ty": 4,
      "nm": "blue-cube Outlines",
      "sr": 1,
      "ks": {
        "o": {
          "a": 0,
          "k": 100,
          "ix": 11
        },
        "r": {
          "a": 0,
          "k": 0,
          "ix": 10
        },
        "p": {
          "s": true,
          "x": {
            "a": 1,
            "k": [
              {
                "i": {
                  "x": [
                    0.775
                  ],
                  "y": [
                    0.978
                  ]
                },
                "o": {
                  "x": [
                    0
                  ],
                  "y": [
                    0
                  ]
                },
                "n": [
                  "0p775_0p978_0_0"
                ],
                "t": 6,
                "s": [
                  516.668
                ],
                "e": [
                  883
                ]
              },
              {
                "t": 38
              }
            ],
            "ix": 3
          },
          "y": {
            "a": 1,
            "k": [
              {
                "i": {
                  "x": [
                    0.833
                  ],
                  "y": [
                    0.833
                  ]
                },
                "o": {
                  "x": [
                    0.167
                  ],
                  "y": [
                    0.167
                  ]
                },
                "n": [
                  "0p833_0p833_0p167_0p167"
                ],
                "t": 0,
                "s": [
                  1404.144
                ],
                "e": [
                  1404.144
                ]
              },
              {
                "i": {
                  "x": [
                    1
                  ],
                  "y": [
                    1
                  ]
                },
                "o": {
                  "x": [
                    0.472
                  ],
                  "y": [
                    1.836
                  ]
                },
                "n": [
                  "1_1_0p472_1p836"
                ],
                "t": 6,
                "s": [
                  1404.144
                ],
                "e": [
                  633
                ]
              },
              {
                "t": 36
              }
            ],
            "ix": 4
          }
        },
        "a": {
          "a": 0,
          "k": [
            31,
            33.5,
            0
          ],
          "ix": 1
        },
        "s": {
          "a": 0,
          "k": [
            238,
            238,
            100
          ],
          "ix": 6
        }
      },
      "ao": 0,
      "shapes": [
        {
          "ty": "gr",
          "it": [
            {
              "ind": 0,
              "ty": "sh",
              "ix": 1,
              "ks": {
                "a": 0,
                "k": {
                  "i": [
                    [
                      0,
                      0
                    ],
                    [
                      0,
                      0
                    ],
                    [
                      0,
                      0
                    ],
                    [
                      0,
                      0
                    ]
                  ],
                  "o": [
                    [
                      0,
                      0
                    ],
                    [
                      0,
                      0
                    ],
                    [
                      0,
                      0
                    ],
                    [
                      0,
                      0
                    ]
                  ],
                  "v": [
                    [
                      -15.492,
                      6.43
                    ],
                    [
                      15.41,
                      24.269
                    ],
                    [
                      15.492,
                      -6.43
                    ],
                    [
                      -15.401,
                      -24.269
                    ]
                  ],
                  "c": true
                },
                "ix": 2
              },
              "nm": "Path 1",
              "mn": "ADBE Vector Shape - Group",
              "hd": false
            },
            {
              "ty": "fl",
              "c": {
                "a": 0,
                "k": [
                  0.325,
                  0.438999998803,
                  0.552999997606,
                  1
                ],
                "ix": 4
              },
              "o": {
                "a": 0,
                "k": 100,
                "ix": 5
              },
              "r": 1,
              "nm": "Fill 1",
              "mn": "ADBE Vector Graphic - Fill",
              "hd": false
            },
            {
              "ty": "tr",
              "p": {
                "a": 0,
                "k": [
                  15.492,
                  42.115
                ],
                "ix": 2
              },
              "a": {
                "a": 0,
                "k": [
                  0,
                  0
                ],
                "ix": 1
              },
              "s": {
                "a": 0,
                "k": [
                  100,
                  100
                ],
                "ix": 3
              },
              "r": {
                "a": 0,
                "k": 0,
                "ix": 6
              },
              "o": {
                "a": 0,
                "k": 100,
                "ix": 7
              },
              "sk": {
                "a": 0,
                "k": 0,
                "ix": 4
              },
              "sa": {
                "a": 0,
                "k": 0,
                "ix": 5
              },
              "nm": "Transform"
            }
          ],
          "nm": "Group 1",
          "np": 2,
          "cix": 2,
          "ix": 1,
          "mn": "ADBE Vector Group",
          "hd": false
        },
        {
          "ty": "gr",
          "it": [
            {
              "ind": 0,
              "ty": "sh",
              "ix": 1,
              "ks": {
                "a": 0,
                "k": {
                  "i": [
                    [
                      0,
                      0
                    ],
                    [
                      0,
                      0
                    ],
                    [
                      0,
                      0
                    ],
                    [
                      0,
                      0
                    ]
                  ],
                  "o": [
                    [
                      0,
                      0
                    ],
                    [
                      0,
                      0
                    ],
                    [
                      0,
                      0
                    ],
                    [
                      0,
                      0
                    ]
                  ],
                  "v": [
                    [
                      -15.307,
                      -6.43
                    ],
                    [
                      -15.391,
                      24.269
                    ],
                    [
                      15.299,
                      6.43
                    ],
                    [
                      15.391,
                      -24.268
                    ]
                  ],
                  "c": true
                },
                "ix": 2
              },
              "nm": "Path 1",
              "mn": "ADBE Vector Shape - Group",
              "hd": false
            },
            {
              "ty": "fl",
              "c": {
                "a": 0,
                "k": [
                  0.430999995213,
                  0.57599995931,
                  0.717999985639,
                  1
                ],
                "ix": 4
              },
              "o": {
                "a": 0,
                "k": 100,
                "ix": 5
              },
              "r": 1,
              "nm": "Fill 1",
              "mn": "ADBE Vector Graphic - Fill",
              "hd": false
            },
            {
              "ty": "tr",
              "p": {
                "a": 0,
                "k": [
                  46.292,
                  42.115
                ],
                "ix": 2
              },
              "a": {
                "a": 0,
                "k": [
                  0,
                  0
                ],
                "ix": 1
              },
              "s": {
                "a": 0,
                "k": [
                  100,
                  100
                ],
                "ix": 3
              },
              "r": {
                "a": 0,
                "k": 0,
                "ix": 6
              },
              "o": {
                "a": 0,
                "k": 100,
                "ix": 7
              },
              "sk": {
                "a": 0,
                "k": 0,
                "ix": 4
              },
              "sa": {
                "a": 0,
                "k": 0,
                "ix": 5
              },
              "nm": "Transform"
            }
          ],
          "nm": "Group 2",
          "np": 2,
          "cix": 2,
          "ix": 2,
          "mn": "ADBE Vector Group",
          "hd": false
        },
        {
          "ty": "gr",
          "it": [
            {
              "ind": 0,
              "ty": "sh",
              "ix": 1,
              "ks": {
                "a": 0,
                "k": {
                  "i": [
                    [
                      0,
                      0
                    ],
                    [
                      0,
                      0
                    ],
                    [
                      0,
                      0
                    ],
                    [
                      0,
                      0
                    ]
                  ],
                  "o": [
                    [
                      0,
                      0
                    ],
                    [
                      0,
                      0
                    ],
                    [
                      0,
                      0
                    ],
                    [
                      0,
                      0
                    ]
                  ],
                  "v": [
                    [
                      -0.106,
                      -17.842
                    ],
                    [
                      -30.796,
                      0.004
                    ],
                    [
                      0.097,
                      17.842
                    ],
                    [
                      30.796,
                      0.004
                    ]
                  ],
                  "c": true
                },
                "ix": 2
              },
              "nm": "Path 1",
              "mn": "ADBE Vector Shape - Group",
              "hd": false
            },
            {
              "ty": "fl",
              "c": {
                "a": 0,
                "k": [
                  0.46699999641,
                  0.62400004069,
                  0.776000019148,
                  1
                ],
                "ix": 4
              },
              "o": {
                "a": 0,
                "k": 100,
                "ix": 5
              },
              "r": 1,
              "nm": "Fill 1",
              "mn": "ADBE Vector Graphic - Fill",
              "hd": false
            },
            {
              "ty": "tr",
              "p": {
                "a": 0,
                "k": [
                  30.887,
                  17.843
                ],
                "ix": 2
              },
              "a": {
                "a": 0,
                "k": [
                  0,
                  0
                ],
                "ix": 1
              },
              "s": {
                "a": 0,
                "k": [
                  100,
                  100
                ],
                "ix": 3
              },
              "r": {
                "a": 0,
                "k": 0,
                "ix": 6
              },
              "o": {
                "a": 0,
                "k": 100,
                "ix": 7
              },
              "sk": {
                "a": 0,
                "k": 0,
                "ix": 4
              },
              "sa": {
                "a": 0,
                "k": 0,
                "ix": 5
              },
              "nm": "Transform"
            }
          ],
          "nm": "Group 3",
          "np": 2,
          "cix": 2,
          "ix": 3,
          "mn": "ADBE Vector Group",
          "hd": false
        }
      ],
      "ip": 0,
      "op": 99,
      "st": 0,
      "bm": 0
    },
    {
      "ddd": 0,
      "ind": 3,
      "ty": 4,
      "nm": "blue-cube Outlines",
      "sr": 1,
      "ks": {
        "o": {
          "a": 0,
          "k": 100,
          "ix": 11
        },
        "r": {
          "a": 0,
          "k": 0,
          "ix": 10
        },
        "p": {
          "s": true,
          "x": {
            "a": 1,
            "k": [
              {
                "i": {
                  "x": [
                    1
                  ],
                  "y": [
                    1.001
                  ]
                },
                "o": {
                  "x": [
                    0.009
                  ],
                  "y": [
                    -0.031
                  ]
                },
                "n": [
                  "1_1p001_0p009_-0p031"
                ],
                "t": 4,
                "s": [
                  79
                ],
                "e": [
                  519
                ]
              },
              {
                "t": 34
              }
            ],
            "ix": 3
          },
          "y": {
            "a": 1,
            "k": [
              {
                "i": {
                  "x": [
                    0.833
                  ],
                  "y": [
                    0.833
                  ]
                },
                "o": {
                  "x": [
                    0.167
                  ],
                  "y": [
                    0.167
                  ]
                },
                "n": [
                  "0p833_0p833_0p167_0p167"
                ],
                "t": 0,
                "s": [
                  1009
                ],
                "e": [
                  1009
                ]
              },
              {
                "i": {
                  "x": [
                    1
                  ],
                  "y": [
                    0.998
                  ]
                },
                "o": {
                  "x": [
                    0.187
                  ],
                  "y": [
                    3.017
                  ]
                },
                "n": [
                  "1_0p998_0p187_3p017"
                ],
                "t": 4,
                "s": [
                  1009
                ],
                "e": [
                  450.243
                ]
              },
              {
                "t": 34
              }
            ],
            "ix": 4
          }
        },
        "a": {
          "a": 0,
          "k": [
            31,
            33.5,
            0
          ],
          "ix": 1
        },
        "s": {
          "a": 0,
          "k": [
            238,
            238,
            100
          ],
          "ix": 6
        }
      },
      "ao": 0,
      "shapes": [
        {
          "ty": "gr",
          "it": [
            {
              "ind": 0,
              "ty": "sh",
              "ix": 1,
              "ks": {
                "a": 0,
                "k": {
                  "i": [
                    [
                      0,
                      0
                    ],
                    [
                      0,
                      0
                    ],
                    [
                      0,
                      0
                    ],
                    [
                      0,
                      0
                    ]
                  ],
                  "o": [
                    [
                      0,
                      0
                    ],
                    [
                      0,
                      0
                    ],
                    [
                      0,
                      0
                    ],
                    [
                      0,
                      0
                    ]
                  ],
                  "v": [
                    [
                      -15.492,
                      6.43
                    ],
                    [
                      15.41,
                      24.269
                    ],
                    [
                      15.492,
                      -6.43
                    ],
                    [
                      -15.401,
                      -24.269
                    ]
                  ],
                  "c": true
                },
                "ix": 2
              },
              "nm": "Path 1",
              "mn": "ADBE Vector Shape - Group",
              "hd": false
            },
            {
              "ty": "fl",
              "c": {
                "a": 0,
                "k": [
                  0.325,
                  0.438999998803,
                  0.552999997606,
                  1
                ],
                "ix": 4
              },
              "o": {
                "a": 0,
                "k": 100,
                "ix": 5
              },
              "r": 1,
              "nm": "Fill 1",
              "mn": "ADBE Vector Graphic - Fill",
              "hd": false
            },
            {
              "ty": "tr",
              "p": {
                "a": 0,
                "k": [
                  15.492,
                  42.115
                ],
                "ix": 2
              },
              "a": {
                "a": 0,
                "k": [
                  0,
                  0
                ],
                "ix": 1
              },
              "s": {
                "a": 0,
                "k": [
                  100,
                  100
                ],
                "ix": 3
              },
              "r": {
                "a": 0,
                "k": 0,
                "ix": 6
              },
              "o": {
                "a": 0,
                "k": 100,
                "ix": 7
              },
              "sk": {
                "a": 0,
                "k": 0,
                "ix": 4
              },
              "sa": {
                "a": 0,
                "k": 0,
                "ix": 5
              },
              "nm": "Transform"
            }
          ],
          "nm": "Group 1",
          "np": 2,
          "cix": 2,
          "ix": 1,
          "mn": "ADBE Vector Group",
          "hd": false
        },
        {
          "ty": "gr",
          "it": [
            {
              "ind": 0,
              "ty": "sh",
              "ix": 1,
              "ks": {
                "a": 0,
                "k": {
                  "i": [
                    [
                      0,
                      0
                    ],
                    [
                      0,
                      0
                    ],
                    [
                      0,
                      0
                    ],
                    [
                      0,
                      0
                    ]
                  ],
                  "o": [
                    [
                      0,
                      0
                    ],
                    [
                      0,
                      0
                    ],
                    [
                      0,
                      0
                    ],
                    [
                      0,
                      0
                    ]
                  ],
                  "v": [
                    [
                      -15.307,
                      -6.43
                    ],
                    [
                      -15.391,
                      24.269
                    ],
                    [
                      15.299,
                      6.43
                    ],
                    [
                      15.391,
                      -24.268
                    ]
                  ],
                  "c": true
                },
                "ix": 2
              },
              "nm": "Path 1",
              "mn": "ADBE Vector Shape - Group",
              "hd": false
            },
            {
              "ty": "fl",
              "c": {
                "a": 0,
                "k": [
                  0.430999995213,
                  0.57599995931,
                  0.717999985639,
                  1
                ],
                "ix": 4
              },
              "o": {
                "a": 0,
                "k": 100,
                "ix": 5
              },
              "r": 1,
              "nm": "Fill 1",
              "mn": "ADBE Vector Graphic - Fill",
              "hd": false
            },
            {
              "ty": "tr",
              "p": {
                "a": 0,
                "k": [
                  46.292,
                  42.115
                ],
                "ix": 2
              },
              "a": {
                "a": 0,
                "k": [
                  0,
                  0
                ],
                "ix": 1
              },
              "s": {
                "a": 0,
                "k": [
                  100,
                  100
                ],
                "ix": 3
              },
              "r": {
                "a": 0,
                "k": 0,
                "ix": 6
              },
              "o": {
                "a": 0,
                "k": 100,
                "ix": 7
              },
              "sk": {
                "a": 0,
                "k": 0,
                "ix": 4
              },
              "sa": {
                "a": 0,
                "k": 0,
                "ix": 5
              },
              "nm": "Transform"
            }
          ],
          "nm": "Group 2",
          "np": 2,
          "cix": 2,
          "ix": 2,
          "mn": "ADBE Vector Group",
          "hd": false
        },
        {
          "ty": "gr",
          "it": [
            {
              "ind": 0,
              "ty": "sh",
              "ix": 1,
              "ks": {
                "a": 0,
                "k": {
                  "i": [
                    [
                      0,
                      0
                    ],
                    [
                      0,
                      0
                    ],
                    [
                      0,
                      0
                    ],
                    [
                      0,
                      0
                    ]
                  ],
                  "o": [
                    [
                      0,
                      0
                    ],
                    [
                      0,
                      0
                    ],
                    [
                      0,
                      0
                    ],
                    [
                      0,
                      0
                    ]
                  ],
                  "v": [
                    [
                      -0.106,
                      -17.842
                    ],
                    [
                      -30.796,
                      0.004
                    ],
                    [
                      0.097,
                      17.842
                    ],
                    [
                      30.796,
                      0.004
                    ]
                  ],
                  "c": true
                },
                "ix": 2
              },
              "nm": "Path 1",
              "mn": "ADBE Vector Shape - Group",
              "hd": false
            },
            {
              "ty": "fl",
              "c": {
                "a": 0,
                "k": [
                  0.46699999641,
                  0.62400004069,
                  0.776000019148,
                  1
                ],
                "ix": 4
              },
              "o": {
                "a": 0,
                "k": 100,
                "ix": 5
              },
              "r": 1,
              "nm": "Fill 1",
              "mn": "ADBE Vector Graphic - Fill",
              "hd": false
            },
            {
              "ty": "tr",
              "p": {
                "a": 0,
                "k": [
                  30.887,
                  17.843
                ],
                "ix": 2
              },
              "a": {
                "a": 0,
                "k": [
                  0,
                  0
                ],
                "ix": 1
              },
              "s": {
                "a": 0,
                "k": [
                  100,
                  100
                ],
                "ix": 3
              },
              "r": {
                "a": 0,
                "k": 0,
                "ix": 6
              },
              "o": {
                "a": 0,
                "k": 100,
                "ix": 7
              },
              "sk": {
                "a": 0,
                "k": 0,
                "ix": 4
              },
              "sa": {
                "a": 0,
                "k": 0,
                "ix": 5
              },
              "nm": "Transform"
            }
          ],
          "nm": "Group 3",
          "np": 2,
          "cix": 2,
          "ix": 3,
          "mn": "ADBE Vector Group",
          "hd": false
        }
      ],
      "ip": 0,
      "op": 99,
      "st": 0,
      "bm": 0
    },
    {
      "ddd": 0,
      "ind": 4,
      "ty": 4,
      "nm": "blue-cube Outlines",
      "sr": 1,
      "ks": {
        "o": {
          "a": 0,
          "k": 100,
          "ix": 11
        },
        "r": {
          "a": 0,
          "k": 0,
          "ix": 10
        },
        "p": {
          "s": true,
          "x": {
            "a": 1,
            "k": [
              {
                "i": {
                  "x": [
                    1
                  ],
                  "y": [
                    1
                  ]
                },
                "o": {
                  "x": [
                    0.14
                  ],
                  "y": [
                    0.127
                  ]
                },
                "n": [
                  "1_1_0p14_0p127"
                ],
                "t": 19,
                "s": [
                  1630
                ],
                "e": [
                  880
                ]
              },
              {
                "t": 37
              }
            ],
            "ix": 3
          },
          "y": {
            "a": 1,
            "k": [
              {
                "i": {
                  "x": [
                    0.833
                  ],
                  "y": [
                    0.833
                  ]
                },
                "o": {
                  "x": [
                    0.167
                  ],
                  "y": [
                    0.167
                  ]
                },
                "n": [
                  "0p833_0p833_0p167_0p167"
                ],
                "t": 0,
                "s": [
                  833
                ],
                "e": [
                  833
                ]
              },
              {
                "i": {
                  "x": [
                    1
                  ],
                  "y": [
                    0.999
                  ]
                },
                "o": {
                  "x": [
                    0.187
                  ],
                  "y": [
                    1.745
                  ]
                },
                "n": [
                  "1_0p999_0p187_1p745"
                ],
                "t": 19,
                "s": [
                  833
                ],
                "e": [
                  253.243
                ]
              },
              {
                "t": 37
              }
            ],
            "ix": 4
          }
        },
        "a": {
          "a": 0,
          "k": [
            31,
            33.5,
            0
          ],
          "ix": 1
        },
        "s": {
          "a": 0,
          "k": [
            238,
            238,
            100
          ],
          "ix": 6
        }
      },
      "ao": 0,
      "shapes": [
        {
          "ty": "gr",
          "it": [
            {
              "ind": 0,
              "ty": "sh",
              "ix": 1,
              "ks": {
                "a": 0,
                "k": {
                  "i": [
                    [
                      0,
                      0
                    ],
                    [
                      0,
                      0
                    ],
                    [
                      0,
                      0
                    ],
                    [
                      0,
                      0
                    ]
                  ],
                  "o": [
                    [
                      0,
                      0
                    ],
                    [
                      0,
                      0
                    ],
                    [
                      0,
                      0
                    ],
                    [
                      0,
                      0
                    ]
                  ],
                  "v": [
                    [
                      -15.492,
                      6.43
                    ],
                    [
                      15.41,
                      24.269
                    ],
                    [
                      15.492,
                      -6.43
                    ],
                    [
                      -15.401,
                      -24.269
                    ]
                  ],
                  "c": true
                },
                "ix": 2
              },
              "nm": "Path 1",
              "mn": "ADBE Vector Shape - Group",
              "hd": false
            },
            {
              "ty": "fl",
              "c": {
                "a": 0,
                "k": [
                  0.325,
                  0.438999998803,
                  0.552999997606,
                  1
                ],
                "ix": 4
              },
              "o": {
                "a": 0,
                "k": 100,
                "ix": 5
              },
              "r": 1,
              "nm": "Fill 1",
              "mn": "ADBE Vector Graphic - Fill",
              "hd": false
            },
            {
              "ty": "tr",
              "p": {
                "a": 0,
                "k": [
                  15.492,
                  42.115
                ],
                "ix": 2
              },
              "a": {
                "a": 0,
                "k": [
                  0,
                  0
                ],
                "ix": 1
              },
              "s": {
                "a": 0,
                "k": [
                  100,
                  100
                ],
                "ix": 3
              },
              "r": {
                "a": 0,
                "k": 0,
                "ix": 6
              },
              "o": {
                "a": 0,
                "k": 100,
                "ix": 7
              },
              "sk": {
                "a": 0,
                "k": 0,
                "ix": 4
              },
              "sa": {
                "a": 0,
                "k": 0,
                "ix": 5
              },
              "nm": "Transform"
            }
          ],
          "nm": "Group 1",
          "np": 2,
          "cix": 2,
          "ix": 1,
          "mn": "ADBE Vector Group",
          "hd": false
        },
        {
          "ty": "gr",
          "it": [
            {
              "ind": 0,
              "ty": "sh",
              "ix": 1,
              "ks": {
                "a": 0,
                "k": {
                  "i": [
                    [
                      0,
                      0
                    ],
                    [
                      0,
                      0
                    ],
                    [
                      0,
                      0
                    ],
                    [
                      0,
                      0
                    ]
                  ],
                  "o": [
                    [
                      0,
                      0
                    ],
                    [
                      0,
                      0
                    ],
                    [
                      0,
                      0
                    ],
                    [
                      0,
                      0
                    ]
                  ],
                  "v": [
                    [
                      -15.307,
                      -6.43
                    ],
                    [
                      -15.391,
                      24.269
                    ],
                    [
                      15.299,
                      6.43
                    ],
                    [
                      15.391,
                      -24.268
                    ]
                  ],
                  "c": true
                },
                "ix": 2
              },
              "nm": "Path 1",
              "mn": "ADBE Vector Shape - Group",
              "hd": false
            },
            {
              "ty": "fl",
              "c": {
                "a": 0,
                "k": [
                  0.430999995213,
                  0.57599995931,
                  0.717999985639,
                  1
                ],
                "ix": 4
              },
              "o": {
                "a": 0,
                "k": 100,
                "ix": 5
              },
              "r": 1,
              "nm": "Fill 1",
              "mn": "ADBE Vector Graphic - Fill",
              "hd": false
            },
            {
              "ty": "tr",
              "p": {
                "a": 0,
                "k": [
                  46.292,
                  42.115
                ],
                "ix": 2
              },
              "a": {
                "a": 0,
                "k": [
                  0,
                  0
                ],
                "ix": 1
              },
              "s": {
                "a": 0,
                "k": [
                  100,
                  100
                ],
                "ix": 3
              },
              "r": {
                "a": 0,
                "k": 0,
                "ix": 6
              },
              "o": {
                "a": 0,
                "k": 100,
                "ix": 7
              },
              "sk": {
                "a": 0,
                "k": 0,
                "ix": 4
              },
              "sa": {
                "a": 0,
                "k": 0,
                "ix": 5
              },
              "nm": "Transform"
            }
          ],
          "nm": "Group 2",
          "np": 2,
          "cix": 2,
          "ix": 2,
          "mn": "ADBE Vector Group",
          "hd": false
        },
        {
          "ty": "gr",
          "it": [
            {
              "ind": 0,
              "ty": "sh",
              "ix": 1,
              "ks": {
                "a": 0,
                "k": {
                  "i": [
                    [
                      0,
                      0
                    ],
                    [
                      0,
                      0
                    ],
                    [
                      0,
                      0
                    ],
                    [
                      0,
                      0
                    ]
                  ],
                  "o": [
                    [
                      0,
                      0
                    ],
                    [
                      0,
                      0
                    ],
                    [
                      0,
                      0
                    ],
                    [
                      0,
                      0
                    ]
                  ],
                  "v": [
                    [
                      -0.106,
                      -17.842
                    ],
                    [
                      -30.796,
                      0.004
                    ],
                    [
                      0.097,
                      17.842
                    ],
                    [
                      30.796,
                      0.004
                    ]
                  ],
                  "c": true
                },
                "ix": 2
              },
              "nm": "Path 1",
              "mn": "ADBE Vector Shape - Group",
              "hd": false
            },
            {
              "ty": "fl",
              "c": {
                "a": 0,
                "k": [
                  0.46699999641,
                  0.62400004069,
                  0.776000019148,
                  1
                ],
                "ix": 4
              },
              "o": {
                "a": 0,
                "k": 100,
                "ix": 5
              },
              "r": 1,
              "nm": "Fill 1",
              "mn": "ADBE Vector Graphic - Fill",
              "hd": false
            },
            {
              "ty": "tr",
              "p": {
                "a": 0,
                "k": [
                  30.887,
                  17.843
                ],
                "ix": 2
              },
              "a": {
                "a": 0,
                "k": [
                  0,
                  0
                ],
                "ix": 1
              },
              "s": {
                "a": 0,
                "k": [
                  100,
                  100
                ],
                "ix": 3
              },
              "r": {
                "a": 0,
                "k": 0,
                "ix": 6
              },
              "o": {
                "a": 0,
                "k": 100,
                "ix": 7
              },
              "sk": {
                "a": 0,
                "k": 0,
                "ix": 4
              },
              "sa": {
                "a": 0,
                "k": 0,
                "ix": 5
              },
              "nm": "Transform"
            }
          ],
          "nm": "Group 3",
          "np": 2,
          "cix": 2,
          "ix": 3,
          "mn": "ADBE Vector Group",
          "hd": false
        }
      ],
      "ip": 0,
      "op": 99,
      "st": 0,
      "bm": 0
    },
    {
      "ddd": 0,
      "ind": 5,
      "ty": 2,
      "nm": "assets@5x.png",
      "cl": "png",
      "refId": "image_0",
      "sr": 1,
      "ks": {
        "o": {
          "a": 0,
          "k": 100,
          "ix": 11
        },
        "r": {
          "a": 0,
          "k": 0,
          "ix": 10
        },
        "p": {
          "a": 0,
          "k": [
            879,
            761,
            0
          ],
          "ix": 2
        },
        "a": {
          "a": 0,
          "k": [
            1276,
            1444.5,
            0
          ],
          "ix": 1
        },
        "s": {
          "a": 0,
          "k": [
            40.521,
            40.521,
            100
          ],
          "ix": 6
        }
      },
      "ao": 0,
      "ip": 0,
      "op": 99,
      "st": 0,
      "bm": 0
    }
  ],
  "markers": []
}